peng3d/__init__.py
peng3d/camera.py
peng3d/config.py
peng3d/i18n.py
peng3d/keybind.py
peng3d/layer.py
peng3d/menu.py
peng3d/model.py
peng3d/peng.py
peng3d/pyglet_patch.py
peng3d/resource.py
peng3d/version.py
peng3d/window.py
peng3d/world.py
peng3d/actor/__init__.py
peng3d/actor/player.py
peng3d/gui/__init__.py
peng3d/gui/button.py
peng3d/gui/container.py
peng3d/gui/layered.py
peng3d/gui/layout.py
peng3d/gui/menus.py
peng3d/gui/slider.py
peng3d/gui/text.py
peng3d/gui/widgets.py
peng3d/util/__init__.py
peng3d/util/gui.py
peng3d-1.11.0.dist-info/LICENSE.md
peng3d-1.11.0.dist-info/METADATA
peng3d-1.11.0.dist-info/WHEEL
peng3d-1.11.0.dist-info/top_level.txt
peng3d-1.11.0.dist-info/RECORD
